mesqual/__init__.py
mesqual-0.0.1a0.dist-info/licenses/LICENSE
mesqual-0.0.1a0.dist-info/METADATA
mesqual-0.0.1a0.dist-info/WHEEL
mesqual-0.0.1a0.dist-info/top_level.txt
mesqual-0.0.1a0.dist-info/RECORD
