Metadata-Version: 2.4
Name: mesqual
Version: 0.0.1a0
Summary: Modular Energy Scenario Qualitative & Quantitative Analysis Library
Author: Helge Esch
License:                    GNU LESSER GENERAL PUBLIC LICENSE
Project-URL: Homepage, https://github.com/helgeesch/mesqual
Project-URL: Issues, https://github.com/helgeesch/mesqual/issues
Classifier: Programming Language :: Python :: 3
Classifier: License :: OSI Approved :: GNU Lesser General Public License v3 (LGPLv3)
Classifier: Operating System :: OS Independent
Requires-Python: >=3.9
License-File: LICENSE
Dynamic: license-file
